polar_sdk/__init__.py
polar_sdk/_hooks/__init__.py
polar_sdk/_hooks/registration.py
polar_sdk/_hooks/sdkhooks.py
polar_sdk/_hooks/types.py
polar_sdk/_version.py
polar_sdk/_webhooks/__init__.py
polar_sdk/basesdk.py
polar_sdk/benefit_grants.py
polar_sdk/benefits.py
polar_sdk/checkout_links.py
polar_sdk/checkouts.py
polar_sdk/clients.py
polar_sdk/custom_fields.py
polar_sdk/customer_meters.py
polar_sdk/customer_portal.py
polar_sdk/customer_seats.py
polar_sdk/customer_session_sdk.py
polar_sdk/customer_sessions.py
polar_sdk/customers.py
polar_sdk/discounts.py
polar_sdk/disputes.py
polar_sdk/downloadables.py
polar_sdk/event_types.py
polar_sdk/events.py
polar_sdk/files.py
polar_sdk/httpclient.py
polar_sdk/ingestion/__init__.py
polar_sdk/ingestion/_base.py
polar_sdk/ingestion/strategies/__init__.py
polar_sdk/ingestion/strategies/_base.py
polar_sdk/ingestion/strategies/pydantic_ai.py
polar_sdk/license_keys.py
polar_sdk/member_sessions.py
polar_sdk/members.py
polar_sdk/meters.py
polar_sdk/metrics_sdk.py
polar_sdk/models/__init__.py
polar_sdk/models/address.py
polar_sdk/models/addressdict.py
polar_sdk/models/addressinput.py
polar_sdk/models/aggregationfunction.py
polar_sdk/models/alreadyactivesubscriptionerror.py
polar_sdk/models/alreadycanceledsubscription.py
polar_sdk/models/attachedcustomfield.py
polar_sdk/models/attachedcustomfieldcreate.py
polar_sdk/models/authorizationcodetokenrequest.py
polar_sdk/models/authorizeorganization.py
polar_sdk/models/authorizeresponseorganization.py
polar_sdk/models/authorizeresponseuser.py
polar_sdk/models/authorizeuser.py
polar_sdk/models/availablescope.py
polar_sdk/models/balancecreditorderevent.py
polar_sdk/models/balancecreditordermetadata.py
polar_sdk/models/balancedisputeevent.py
polar_sdk/models/balancedisputemetadata.py
polar_sdk/models/balancedisputereversalevent.py
polar_sdk/models/balanceorderevent.py
polar_sdk/models/balanceordermetadata.py
polar_sdk/models/balancerefundevent.py
polar_sdk/models/balancerefundmetadata.py
polar_sdk-0.28.4.dist-info/METADATA
polar_sdk-0.28.4.dist-info/WHEEL
polar_sdk-0.28.4.dist-info/RECORD
